{
  "name": "amp-cli",
  "version": "0.0.0",
  "lockfileVersion": 3,
  "requires": true,
  "packages": {
    "": {
      "name": "amp-cli",
      "version": "0.0.0",
      "license": "UNLICENSED",
      "dependencies": {
        "@sourcegraph/amp": "0.0.1779639467-g6d0650"
      },
      "bin": {
        "amp": "bin/amp-wrapper.js"
      }
    },
    "node_modules/@ampcode/cli": {
      "version": "0.0.1779639467-g6d0650",
      "resolved": "https://registry.npmjs.org/@ampcode/cli/-/cli-0.0.1779639467-g6d0650.tgz",
      "integrity": "sha512-eI0d27iXcqCIjPJI1kg3MYdCFruxD8V7CwbadNbTgztQ+LWdTWEvvwICBaN9t+uoUUWOvMR9wWH8s1UYwJS45Q==",
      "hasInstallScript": true,
      "license": "SEE LICENSE IN LICENSE.md",
      "bin": {
        "amp": "bin/amp.exe"
      },
      "optionalDependencies": {
        "@ampcode/cli-darwin-arm64": "0.0.1779639467-g6d0650",
        "@ampcode/cli-darwin-x64": "0.0.1779639467-g6d0650",
        "@ampcode/cli-linux-arm64": "0.0.1779639467-g6d0650",
        "@ampcode/cli-linux-x64": "0.0.1779639467-g6d0650",
        "@ampcode/cli-win32-x64": "0.0.1779639467-g6d0650"
      }
    },
    "node_modules/@ampcode/cli-darwin-arm64": {
      "version": "0.0.1779639467-g6d0650",
      "resolved": "https://registry.npmjs.org/@ampcode/cli-darwin-arm64/-/cli-darwin-arm64-0.0.1779639467-g6d0650.tgz",
      "integrity": "sha512-BYm4tUgDNR3PjUyIRcB7PqO2MedF1vyz2R+zlbmBPHl4+zTo9P1Fj+taH+DWqlw9SDdSHl7GEpBBwMhz6ZYD2w==",
      "cpu": [
        "arm64"
      ],
      "license": "SEE LICENSE IN LICENSE.md",
      "optional": true,
      "os": [
        "darwin"
      ]
    },
    "node_modules/@ampcode/cli-darwin-x64": {
      "version": "0.0.1779639467-g6d0650",
      "resolved": "https://registry.npmjs.org/@ampcode/cli-darwin-x64/-/cli-darwin-x64-0.0.1779639467-g6d0650.tgz",
      "integrity": "sha512-nNKGZJ8/wnUbWOVgka7+aiX4PC0fDLIDOPxIkM/LinVxgMaUp5Nd9I0WXE1AcZbqFSVx8841psT8sZj/uWuRfw==",
      "cpu": [
        "x64"
      ],
      "license": "SEE LICENSE IN LICENSE.md",
      "optional": true,
      "os": [
        "darwin"
      ]
    },
    "node_modules/@ampcode/cli-linux-arm64": {
      "version": "0.0.1779639467-g6d0650",
      "resolved": "https://registry.npmjs.org/@ampcode/cli-linux-arm64/-/cli-linux-arm64-0.0.1779639467-g6d0650.tgz",
      "integrity": "sha512-0bvkCxOBnqv76D9NXp3qDM7ECCa3fi0NtJ0Z07XuvyRPTR9xtyV+tnWJ4Tqs+WkUZMqdv2rnsAW+fBdGHd3z/g==",
      "cpu": [
        "arm64"
      ],
      "license": "SEE LICENSE IN LICENSE.md",
      "optional": true,
      "os": [
        "linux"
      ]
    },
    "node_modules/@ampcode/cli-linux-x64": {
      "version": "0.0.1779639467-g6d0650",
      "resolved": "https://registry.npmjs.org/@ampcode/cli-linux-x64/-/cli-linux-x64-0.0.1779639467-g6d0650.tgz",
      "integrity": "sha512-SnMAIuML6uatMifGOcVRNOed0LBal7Do0bdbFHB7/29UX+3Tw4NN/1gv3H/gj0ArpSs+G3ecPLr9SHgZ7GZOcA==",
      "cpu": [
        "x64"
      ],
      "license": "SEE LICENSE IN LICENSE.md",
      "optional": true,
      "os": [
        "linux"
      ]
    },
    "node_modules/@ampcode/cli-win32-x64": {
      "version": "0.0.1779639467-g6d0650",
      "resolved": "https://registry.npmjs.org/@ampcode/cli-win32-x64/-/cli-win32-x64-0.0.1779639467-g6d0650.tgz",
      "integrity": "sha512-TPWoM+JXagbcPvlPbz4vZ8x33NSPNauR3vINVckc37hWAsTA59YbchGO/m1///CXWcvwjW1npFV9GaszS/ix0A==",
      "cpu": [
        "x64"
      ],
      "license": "SEE LICENSE IN LICENSE.md",
      "optional": true,
      "os": [
        "win32"
      ]
    },
    "node_modules/@sourcegraph/amp": {
      "version": "0.0.1779639467-g6d0650",
      "resolved": "https://registry.npmjs.org/@sourcegraph/amp/-/amp-0.0.1779639467-g6d0650.tgz",
      "integrity": "sha512-oOL4npSxAWAueXdWAzJM4X26lXCSmro0T1b7RMiEfZfQdgHQfdv+skwoRe//jV8xGvZKY6MKz/hAArL+nmL8eQ==",
      "license": "SEE LICENSE IN LICENSE.md",
      "dependencies": {
        "@ampcode/cli": "0.0.1779639467-g6d0650"
      },
      "bin": {
        "amp": "node_modules/@ampcode/cli/bin/amp.exe"
      }
    }
  }
}
