{
  "name": "amp-cli",
  "version": "0.0.0",
  "lockfileVersion": 3,
  "requires": true,
  "packages": {
    "": {
      "name": "amp-cli",
      "version": "0.0.0",
      "license": "UNLICENSED",
      "dependencies": {
        "@sourcegraph/amp": "0.0.1779686836-g4ef406"
      },
      "bin": {
        "amp": "bin/amp-wrapper.js"
      }
    },
    "node_modules/@ampcode/cli": {
      "version": "0.0.1779686836-g4ef406",
      "resolved": "https://registry.npmjs.org/@ampcode/cli/-/cli-0.0.1779686836-g4ef406.tgz",
      "integrity": "sha512-0OzK7Bn+osHISBM3upCQVg0tQADqOtP4t72enDxKxGBmunUYs3ZiGG+SeVNU6seR9P5+mSfvemV1rt7TmWAGTg==",
      "hasInstallScript": true,
      "license": "SEE LICENSE IN LICENSE.md",
      "bin": {
        "amp": "bin/amp.exe"
      },
      "optionalDependencies": {
        "@ampcode/cli-darwin-arm64": "0.0.1779686836-g4ef406",
        "@ampcode/cli-darwin-x64": "0.0.1779686836-g4ef406",
        "@ampcode/cli-linux-arm64": "0.0.1779686836-g4ef406",
        "@ampcode/cli-linux-x64": "0.0.1779686836-g4ef406",
        "@ampcode/cli-win32-x64": "0.0.1779686836-g4ef406"
      }
    },
    "node_modules/@ampcode/cli-darwin-arm64": {
      "version": "0.0.1779686836-g4ef406",
      "resolved": "https://registry.npmjs.org/@ampcode/cli-darwin-arm64/-/cli-darwin-arm64-0.0.1779686836-g4ef406.tgz",
      "integrity": "sha512-nrTKnnUWP4FbbH4Zom2RNBiqJHntgh0dDThkovlDnDvHIaRwe01p36p1B48A9Kzi5Co++9NlEZXtACyKXMKH6Q==",
      "cpu": [
        "arm64"
      ],
      "license": "SEE LICENSE IN LICENSE.md",
      "optional": true,
      "os": [
        "darwin"
      ]
    },
    "node_modules/@ampcode/cli-darwin-x64": {
      "version": "0.0.1779686836-g4ef406",
      "resolved": "https://registry.npmjs.org/@ampcode/cli-darwin-x64/-/cli-darwin-x64-0.0.1779686836-g4ef406.tgz",
      "integrity": "sha512-XS4mpOEcGns5yQoRKzIZlKEY2Zp23jfxAjURSPkCFtR8jXgDenu+7dX1rIqvokJZRgJqacatHRj3H7WzcmdG8Q==",
      "cpu": [
        "x64"
      ],
      "license": "SEE LICENSE IN LICENSE.md",
      "optional": true,
      "os": [
        "darwin"
      ]
    },
    "node_modules/@ampcode/cli-linux-arm64": {
      "version": "0.0.1779686836-g4ef406",
      "resolved": "https://registry.npmjs.org/@ampcode/cli-linux-arm64/-/cli-linux-arm64-0.0.1779686836-g4ef406.tgz",
      "integrity": "sha512-fZdqV8Uib0JCkeGFpst2zdp7wbREVPZ3PFeNp8KUhVvyPefE+6L8RjYW+9enZRLguhUSYNGq8bkiDe2D1K4rqA==",
      "cpu": [
        "arm64"
      ],
      "license": "SEE LICENSE IN LICENSE.md",
      "optional": true,
      "os": [
        "linux"
      ]
    },
    "node_modules/@ampcode/cli-linux-x64": {
      "version": "0.0.1779686836-g4ef406",
      "resolved": "https://registry.npmjs.org/@ampcode/cli-linux-x64/-/cli-linux-x64-0.0.1779686836-g4ef406.tgz",
      "integrity": "sha512-ofQM/z/t+Dgxa9zfblsIbPkpp7VMpOOGcbIGtdrTw+hG4iZ4RCs8gGxjTegAHBHRIyirMOY/HELe8xtWN1OUMQ==",
      "cpu": [
        "x64"
      ],
      "license": "SEE LICENSE IN LICENSE.md",
      "optional": true,
      "os": [
        "linux"
      ]
    },
    "node_modules/@ampcode/cli-win32-x64": {
      "version": "0.0.1779686836-g4ef406",
      "resolved": "https://registry.npmjs.org/@ampcode/cli-win32-x64/-/cli-win32-x64-0.0.1779686836-g4ef406.tgz",
      "integrity": "sha512-ecfoS8PhHI8Q8e/6M965HiP5Nus+hEmvSg4gXkzsQ0pBXbLhfnYT16+GJz9YZuW+56xO3uKt4QcbIhIBBiWdLQ==",
      "cpu": [
        "x64"
      ],
      "license": "SEE LICENSE IN LICENSE.md",
      "optional": true,
      "os": [
        "win32"
      ]
    },
    "node_modules/@sourcegraph/amp": {
      "version": "0.0.1779686836-g4ef406",
      "resolved": "https://registry.npmjs.org/@sourcegraph/amp/-/amp-0.0.1779686836-g4ef406.tgz",
      "integrity": "sha512-Ae6xCNYmFo9Dy4OhPLe+KxJOZkELpt6Ol7sZNNFGidtegx38pzWnsqACH4BR+NoF8MlpI5JAd5LsfJC4oKzELw==",
      "license": "SEE LICENSE IN LICENSE.md",
      "dependencies": {
        "@ampcode/cli": "0.0.1779686836-g4ef406"
      },
      "bin": {
        "amp": "node_modules/@ampcode/cli/bin/amp.exe"
      }
    }
  }
}
